README.md
pyproject.toml
trustgraph/__init__.py
trustgraph/embeddings_hf_version.py
trustgraph/embeddings/__init__.py
trustgraph/embeddings/hf/__init__.py
trustgraph/embeddings/hf/__main__.py
trustgraph/embeddings/hf/hf.py
trustgraph_embeddings_hf.egg-info/PKG-INFO
trustgraph_embeddings_hf.egg-info/SOURCES.txt
trustgraph_embeddings_hf.egg-info/dependency_links.txt
trustgraph_embeddings_hf.egg-info/entry_points.txt
trustgraph_embeddings_hf.egg-info/requires.txt
trustgraph_embeddings_hf.egg-info/top_level.txt