Metadata-Version: 2.4
Name: trustgraph-embeddings-hf
Version: 1.8.2
Summary: HuggingFace embeddings support for TrustGraph.
Author-email: "trustgraph.ai" <security@trustgraph.ai>
Project-URL: Homepage, https://github.com/trustgraph-ai/trustgraph
Classifier: Programming Language :: Python :: 3
Classifier: Operating System :: OS Independent
Requires-Python: >=3.8
Requires-Dist: trustgraph-base<1.9,>=1.8
Requires-Dist: trustgraph-flow<1.9,>=1.8
Requires-Dist: torch
Requires-Dist: urllib3
Requires-Dist: transformers
Requires-Dist: sentence-transformers
Requires-Dist: langchain
Requires-Dist: langchain-core
Requires-Dist: langchain-huggingface
Requires-Dist: langchain-community
Requires-Dist: huggingface-hub
Requires-Dist: pulsar-client
Requires-Dist: pyyaml
Requires-Dist: prometheus-client
